sqlpkg.py
sqlpkg-0.1.dist-info/LICENSE
sqlpkg-0.1.dist-info/WHEEL
sqlpkg-0.1.dist-info/METADATA
sqlpkg-0.1.dist-info/RECORD
