Metadata-Version: 2.1
Name: sqlpkg
Version: 0.1
Summary: SQLite Package Manager for Python
Author-email: Anton Zhiyanov <m@antonz.org>
Classifier: License :: OSI Approved :: MIT License
Project-URL: Home, https://github.com/nalgeon/sqlpkg-py
